ti83chainsaw/__init__.py
ti83chainsaw/var83p.py
ti83chainsaw-0.0.1.dist-info/LICENCE
ti83chainsaw-0.0.1.dist-info/METADATA
ti83chainsaw-0.0.1.dist-info/WHEEL
ti83chainsaw-0.0.1.dist-info/top_level.txt
ti83chainsaw-0.0.1.dist-info/RECORD
