Metadata-Version: 2.1
Name: ti83chainsaw
Version: 0.0.1
Summary: A 83p chainsaw
Home-page: https://github.com/thibaultduponchelle/ti83chainsaw
Author: Thibault DUPONCHELLE
Author-email: thibault.duponchelle@gmail.com
License: UNKNOWN
Project-URL: Bug Tracker, https://github.com/thibaultuponchelle/ti83chainsaw/issues
Platform: UNKNOWN
Classifier: Programming Language :: Python :: 3
Classifier: License :: OSI Approved :: MIT License
Classifier: Operating System :: OS Independent
Requires-Python: >=3.6
